srpenergy/__init__.py
srpenergy/client.py
srpenergy-1.3.7.dist-info/LICENSE
srpenergy-1.3.7.dist-info/METADATA
srpenergy-1.3.7.dist-info/WHEEL
srpenergy-1.3.7.dist-info/top_level.txt
srpenergy-1.3.7.dist-info/RECORD
