Metadata-Version: 2.1
Name: srpenergy
Version: 1.3.7
Summary: An unofficial Python module for interacting with Srp Energy data.
Author-email: Lamoreaux Lab <info@golamoreaux.com>
License: MIT
Project-URL: Homepage, https://github.com/lamoreauxlab/srpenergy-api-client-python
Project-URL: Source Code, https://github.com/lamoreauxlab/srpenergy-api-client-python.git
Project-URL: Bug Reports, https://github.com/lamoreauxlab/srpenergy-api-client-python/issues
Platform: any
Classifier: Development Status :: 5 - Production/Stable
Classifier: Intended Audience :: Developers
Classifier: License :: OSI Approved :: MIT License
Classifier: Operating System :: OS Independent
Classifier: Programming Language :: Python :: 3.10
Classifier: Topic :: Utilities
Requires-Python: >=3.9
License-File: LICENSE
